isic.py
isic-1.0.4.dist-info/LICENSE
isic-1.0.4.dist-info/METADATA
isic-1.0.4.dist-info/WHEEL
isic-1.0.4.dist-info/top_level.txt
isic-1.0.4.dist-info/RECORD
