Metadata-Version: 2.1
Name: isic
Version: 1.0.4
Summary: A Python wrapper around the UN's ISIC definitions
Home-page: https://gitlab.com/workfinder/isic
Author: Daniel Quinn
Author-email: code@danielquinn.org
License: GPL3
Platform: UNKNOWN
Classifier: License :: OSI Approved :: GNU General Public License v3 (GPLv3)
Classifier: Programming Language :: Python
Classifier: Programming Language :: Python :: 3
